pyonrails/__init__.py
pyonrails/orm/__init__.py
pyonrails/orm/base.py
pyonrails-0.0.3.dist-info/LICENSE.txt
pyonrails-0.0.3.dist-info/METADATA
pyonrails-0.0.3.dist-info/WHEEL
pyonrails-0.0.3.dist-info/top_level.txt
pyonrails-0.0.3.dist-info/RECORD
