Metadata-Version: 2.1
Name: pyonrails
Version: 0.0.3
Summary: Python on rails?
Home-page: UNKNOWN
Author: Ryan Johnson
Author-email: jtronixdev@gmail.com
License: MIT
Keywords: python
Platform: UNKNOWN
Classifier: Development Status :: 5 - Production/Stable
Classifier: Intended Audience :: Education
Classifier: Operating System :: Microsoft :: Windows :: Windows 10
Classifier: License :: OSI Approved :: MIT License
Classifier: Programming Language :: Python :: 3
License-File: LICENSE.txt
